AUTHORS
LICENSE
MANIFEST.in
README.md
setup.py
virtenviro/__init__.py
virtenviro/abstract_models.py
virtenviro/logger.py
virtenviro/required_settings.py
virtenviro/sample_settings.py
virtenviro/urls.py
virtenviro/urls_new.py
virtenviro/urls_old.py
virtenviro/utils.py
virtenviro/virtenviro_context_processors.py
virtenviro/wsgi.py
virtenviro.egg-info/PKG-INFO
virtenviro.egg-info/SOURCES.txt
virtenviro.egg-info/dependency_links.txt
virtenviro.egg-info/requires.txt
virtenviro.egg-info/top_level.txt
virtenviro/admin/__init__.py
virtenviro/admin/urls.py
virtenviro/admin/urls_new.py
virtenviro/admin/urls_old.py
virtenviro/admin/utils.py
virtenviro/admin/views.py
virtenviro/admin/templatetags/__init__.py
virtenviro/auto_adv/__init__.py
virtenviro/auto_adv/admin.py
virtenviro/auto_adv/managers.py
virtenviro/auto_adv/models.py
virtenviro/auto_adv/tests.py
virtenviro/auto_adv/views.py
virtenviro/auto_adv/migrations/__init__.py
virtenviro/book/__init__.py
virtenviro/book/admin.py
virtenviro/book/models.py
virtenviro/book/tests.py
virtenviro/book/views.py
virtenviro/book/migrations/__init__.py
virtenviro/content/__init__.py
virtenviro/content/admin.py
virtenviro/content/admin_forms.py
virtenviro/content/admin_urls.py
virtenviro/content/admin_views.py
virtenviro/content/managers.py
virtenviro/content/models.py
virtenviro/content/tests.py
virtenviro/content/urls.py
virtenviro/content/urls_new.py
virtenviro/content/urls_old.py
virtenviro/content/views.py
virtenviro/content/management/__init__.py
virtenviro/content/management/commands/__init__.py
virtenviro/content/management/commands/import_content.py
virtenviro/content/management/commands/import_content2.py
virtenviro/content/migrations/0001_initial.py
virtenviro/content/migrations/0002_auto_20160119_2053.py
virtenviro/content/migrations/__init__.py
virtenviro/content/templatetags/__init__.py
virtenviro/content/templatetags/adsense.py
virtenviro/content/templatetags/page_tags.py
virtenviro/form_constructor/__init__.py
virtenviro/form_constructor/admin.py
virtenviro/form_constructor/forms.py
virtenviro/form_constructor/models.py
virtenviro/form_constructor/tests.py
